spoppy/__init__.py
spoppy/config.py
spoppy/connectivity.py
spoppy/dbus_listener.py
spoppy/http_server.py
spoppy/lifecycle.py
spoppy/logging_utils.py
spoppy/menus.py
spoppy/navigation.py
spoppy/players.py
spoppy/radio.py
spoppy/responses.py
spoppy/sink.py
spoppy/spotify_appkey.key
spoppy/spotipy_wrapper.py
spoppy/terminal.py
spoppy/update_checker.py
spoppy/util.py
spoppy/loaders/__init__.py
spoppy/loaders/loader.py
spoppy/loaders/playlists.py
spoppy/loaders/search.py
spoppy/loaders/tracks.py
spoppy-2.4.0.data/scripts/spoppy
spoppy-2.4.0.dist-info/LICENSE
spoppy-2.4.0.dist-info/METADATA
spoppy-2.4.0.dist-info/WHEEL
spoppy-2.4.0.dist-info/top_level.txt
spoppy-2.4.0.dist-info/RECORD
