Metadata-Version: 2.1
Name: spoppy
Version: 2.4.0
Summary: A lightweight spotify CLI
Home-page: https://github.com/sindrig/spoppy
Author: Sindri Guðmundsson
Author-email: sindrigudmundsson@gmail.com
License: MIT
Keywords: spoppy spotify cli
Platform: UNKNOWN
Classifier: Environment :: Console
Classifier: Intended Audience :: End Users/Desktop
Classifier: License :: OSI Approved :: MIT License
Classifier: Natural Language :: English
Classifier: Operating System :: POSIX :: Linux
Classifier: Operating System :: Unix
Classifier: Programming Language :: Python :: 2.7
Classifier: Programming Language :: Python :: 3.3
Classifier: Programming Language :: Python :: 3.4
Classifier: Programming Language :: Python :: 3.5
Classifier: Topic :: Multimedia :: Sound/Audio
Requires-Dist: click (>=7.0)
Requires-Dist: pyspotify (>=2.0.5)
Requires-Dist: appdirs (>=1.4.3)
Requires-Dist: requests (>=2.21.0)
Requires-Dist: lockfile (>=0.12.2)
Requires-Dist: nose (>=1.3.7)
Requires-Dist: mock (>=2.0.0)
Requires-Dist: spotipy (==2.4.4)
Requires-Dist: twine (==1.13.0)
